tzmerkle/__init__.py
tzmerkle/hashes.py
tzmerkle/merkle.py
tzmerkle/smartpy/merkle_utils.py
tzmerkle-0.2.2.dist-info/licenses/LICENSE
tzmerkle-0.2.2.dist-info/METADATA
tzmerkle-0.2.2.dist-info/WHEEL
tzmerkle-0.2.2.dist-info/top_level.txt
tzmerkle-0.2.2.dist-info/RECORD
