Metadata-Version: 2.4
Name: tzmerkle
Version: 0.2.2
Summary: A Merkle tree implementation for Tezos
Author-email: Timothy Mc Alister <timothy@mcalister.ch>
License-Expression: MIT
Project-URL: Homepage, https://github.com/objkt-com/tzmerkle
Project-URL: Repository, https://github.com/objkt-com/tzmerkle
Project-URL: Bug Tracker, https://github.com/objkt-com/tzmerkle/issues
Classifier: Development Status :: 3 - Alpha
Classifier: Intended Audience :: Developers
Classifier: Topic :: Software Development :: Libraries :: Python Modules
Classifier: Programming Language :: Python :: 3.12
Requires-Python: >=3.12
License-File: LICENSE
Requires-Dist: pytezos
Requires-Dist: pycryptodome
Requires-Dist: tezos-smartpy
Provides-Extra: dev
Requires-Dist: pytest>=7.0; extra == "dev"
Requires-Dist: pytest-cov>=4.0; extra == "dev"
Requires-Dist: black>=23.0; extra == "dev"
Requires-Dist: flake8>=6.0; extra == "dev"
Requires-Dist: build>=1.0; extra == "dev"
Requires-Dist: twine>=4.0; extra == "dev"
Dynamic: license-file
